{
  "required": true,
  "package": "com.redlimerl.speedrunigt.mixins",
  "plugin": "com.redlimerl.speedrunigt.SpeedRunIGTMixinPlugin",
  "compatibilityLevel": "JAVA_17",
  "mixins": [
    "EndPortalBlockMixin",
    "LivingEntityMixin",
    "PlayerAdvancementTrackerMixin",
    "SeedCommandMixin",
    "ServerStatHandlerMixin",
    "ServerWorldMixin",
    "access.ServerStatHandlerAccessor",
    "coop.PlayerManagerMixin",
    "coop.TimeCommandMixin",
    "network.CustomPayloadC2SPacketAccessor",
    "network.ServerPlayNetworkHandlerMixin",
    "timeline.ServerPlayerEntityMixin"
  ],
  "client": [
    "ClientAdvancementManagerMixin",
    "ClientPlayerEntityMixin",
    "ClientWorldMixin",
    "InGameHudMixin",
    "KeyBindingMixin",
    "MinecraftClientMixin",
    "MouseMixin",
    "access.DoubleOptionSliderWidgetAccessor",
    "access.FontManagerAccessor",
    "access.FontStorageAccessor",
    "access.MinecraftClientAccessor",
    "access.MinecraftClientAccessorForAttack",
    "access.WorldRendererAccessor",
    "keybinding.GameOptionsMixin",
    "keybinding.KeyBindingAccessor",
    "network.ClientPlayNetworkHandlerMixin",
    "retime.OptionButtonWidgetMixin",
    "retime.OptionScreenMixin",
    "retime.OptionSliderWidgetMixin",
    "retime.SodiumOptionImplMixin",
    "screen.CreditsScreenMixin",
    "screen.DownloadingTerrainScreenMixin",
    "screen.GameMenuScreenMixin",
    "screen.GeneratorOptionsMixin",
    "screen.OptionsScreenMixin",
    "server.IntegratedServerMixin",
    "timeline.SoundSystemMixin",
    "translate.TranslationStorageMixin"
  ],
  "server": [
    "server.DedicatedServerMixin"
  ],
  "injectors": {
    "defaultRequire": 1
  }
}
