{
  "required": true,
  "minVersion": "0.8",
  "package": "com.redlimerl.speedrunigt.mixins",
  "compatibilityLevel": "JAVA_8",
  "mixins": [
    "LivingEntityMixin",
    "ServerStatHandlerMixin",
    "WorldMixin",
    "access.LevelStorageAccessor",
    "access.ServerStatHandlerAccessor",
    "coop.PlayerManagerMixin",
    "coop.TimeCommandMixin",
    "network.ServerPlayNetworkHandlerMixin",
    "server.DedicatedServerMixin",
    "timeline.ServerPlayerEntityMixin",
    "timeline.VillagerEntityMixin"
  ],
  "client": [
    "AchievementNotificationMixin",
    "ClientPlayerEntityMixin",
    "ClientWorldMixin",
    "GameRendererMixin",
    "KeyBindingMixin",
    "MinecraftClientMixin",
    "ServerStatHandlerMixin",
    "WorldRendererMixin",
    "access.ButtonWidgetAccessor",
    "access.ClientChunkProviderAccessor",
    "access.MinecraftClientAccessorForAttack",
    "access.WorldRendererAccessor",
    "keybinding.GameOptionsMixin",
    "keybinding.KeyBindingAccessor",
    "network.ClientPlayNetworkHandlerMixin",
    "retime.OptionButtonWidgetMixin",
    "retime.accessor.OptionSliderWidgetAccessor",
    "screen.CreditsScreenMixin",
    "screen.DownloadingTerrainScreenMixin",
    "screen.GameMenuScreenMixin",
    "screen.OptionsScreenMixin",
    "screen.WorldOptionsScreenMixin",
    "server.IntegratedServerMixin",
    "translate.I18nMixin",
    "translate.TranslatableTextMixin"
  ],
  "injectors": {
    "defaultRequire": 1
  }
}
